SecuPy/__init__.py
SecuPy/access_control.py
SecuPy/auditing.py
SecuPy/compliance.py
SecuPy/data_privacy_framework.py
SecuPy/documentation.py
secure_learn-0.2.2.dist-info/LICENSE
secure_learn-0.2.2.dist-info/METADATA
secure_learn-0.2.2.dist-info/WHEEL
secure_learn-0.2.2.dist-info/top_level.txt
secure_learn-0.2.2.dist-info/RECORD
