Metadata-Version: 2.1
Name: secure-learn
Version: 0.2.2
Summary: Protect sensitive data with secure-learn, a Python package offering encryption, anonymization, and compliance tools for data scientists.
Home-page: https://github.com/DeependraVerma/SecuPy-Secure-Data-Privacy-Framework-for-Python-Data-Scientists
Author: DeependraVerma
Author-email: deependra.verma00@gmail.com
License: MIT
Project-URL: Bug Tracker, https://github.com/DeependraVerma/SecuPy-Secure-Data-Privacy-Framework-for-Python-Data-Scientists/issues
Classifier: Programming Language :: Python :: 3
Classifier: License :: OSI Approved :: MIT License
Classifier: Operating System :: OS Independent
License-File: LICENSE
Requires-Dist: pandas
Requires-Dist: faker
Requires-Dist: cryptography
Provides-Extra: testing
Requires-Dist: pytest >=7.1.3 ; extra == 'testing'
Requires-Dist: mypy >=0.971 ; extra == 'testing'
Requires-Dist: flake8 >=5.0.4 ; extra == 'testing'
Requires-Dist: tox >=3.25.1 ; extra == 'testing'
Requires-Dist: black >=22.8.0 ; extra == 'testing'
